ReEncrypt.py
ReEncrypt-1.1.0.dist-info/DESCRIPTION.rst
ReEncrypt-1.1.0.dist-info/METADATA
ReEncrypt-1.1.0.dist-info/RECORD
ReEncrypt-1.1.0.dist-info/WHEEL
ReEncrypt-1.1.0.dist-info/metadata.json
ReEncrypt-1.1.0.dist-info/top_level.txt
